cudf_polars/VERSION
cudf_polars/__init__.py
cudf_polars/_version.py
cudf_polars/callback.py
cudf_polars/py.typed
cudf_polars/containers/__init__.py
cudf_polars/containers/column.py
cudf_polars/containers/dataframe.py
cudf_polars/dsl/__init__.py
cudf_polars/dsl/expr.py
cudf_polars/dsl/ir.py
cudf_polars/dsl/translate.py
cudf_polars/testing/__init__.py
cudf_polars/testing/asserts.py
cudf_polars/typing/__init__.py
cudf_polars/utils/__init__.py
cudf_polars/utils/dtypes.py
cudf_polars/utils/sorting.py
cudf_polars_cu11-24.8.0a281.dist-info/LICENSE
cudf_polars_cu11-24.8.0a281.dist-info/METADATA
cudf_polars_cu11-24.8.0a281.dist-info/WHEEL
cudf_polars_cu11-24.8.0a281.dist-info/top_level.txt
cudf_polars_cu11-24.8.0a281.dist-info/RECORD
