Metadata-Version: 2.1
Name: cudf-polars-cu11
Version: 24.8.0a281
Summary: Executor for polars using cudf
Author: NVIDIA Corporation
License: Apache 2.0
Project-URL: Homepage, https://github.com/rapidsai/cudf
Classifier: Intended Audience :: Developers
Classifier: Topic :: Database
Classifier: Topic :: Scientific/Engineering
Classifier: License :: OSI Approved :: Apache Software License
Classifier: Programming Language :: Python
Classifier: Programming Language :: Python :: 3.9
Classifier: Programming Language :: Python :: 3.10
Classifier: Programming Language :: Python :: 3.11
Requires-Python: >=3.9
License-File: LICENSE
Requires-Dist: cudf-cu11 ==24.8.*,>=0.0.0a0
Requires-Dist: polars >=1.0
Provides-Extra: test
Requires-Dist: pytest-cov ; extra == 'test'
Requires-Dist: pytest-xdist ; extra == 'test'
Requires-Dist: pytest <8 ; extra == 'test'
